pltfront/__init__.py
pltfront/factory.py
pltfront/plot.py
pltfront/sauerkraut.py
pltfront-0.4.6.dist-info/LICENSE
pltfront-0.4.6.dist-info/METADATA
pltfront-0.4.6.dist-info/WHEEL
pltfront-0.4.6.dist-info/top_level.txt
pltfront-0.4.6.dist-info/RECORD
