Metadata-Version: 2.1
Name: pltfront
Version: 0.4.6
Summary: A simplified matplotlib frontend
Author-email: Iacopo Ricci <dummy@dummy.com>
License: GPLv3
Project-URL: repository, https://framagit.org/codutils/pltfront
Project-URL: homepage, https://codutils.frama.io/pltfront/tutorial
Project-URL: documentation, https://codutils.frama.io/pltfront/api/pltfront
Classifier: License :: OSI Approved :: GNU General Public License v3 (GPLv3)
Classifier: Programming Language :: Python :: 3.10
Classifier: Development Status :: 4 - Beta
Requires-Python: >=3.10
License-File: LICENSE
Requires-Dist: matplotlib >=3.8.0
Requires-Dist: numpy >=1.26.0
